pybind11_union_find_.cpython-38-x86_64-linux-gnu.so
pybind11_union_find-0.0.2.dist-info/RECORD
pybind11_union_find-0.0.2.dist-info/LICENSE
pybind11_union_find-0.0.2.dist-info/WHEEL
pybind11_union_find-0.0.2.dist-info/METADATA
pybind11_union_find-0.0.2.dist-info/top_level.txt
pybind11_union_find/__init__.py
