Metadata-Version: 2.1
Name: pybind11-union-find
Version: 0.0.2
Summary: UnionFind in C++, with python binding
Home-page: https://pybind11-union-find.readthedocs.io
Author: tzx
Author-email: dvorak4tzx@gmail.com
Requires-Python: >=3.7
License-File: LICENSE
Provides-Extra: test
Requires-Dist: pytest (>=6.0) ; extra == 'test'
